calmjs.sassy-1.0.2-py3.5-nspkg.pth
calmjs/sassy/__init__.py
calmjs/sassy/artifact.py
calmjs/sassy/cli.py
calmjs/sassy/dist.py
calmjs/sassy/exc.py
calmjs/sassy/libsass.py
calmjs/sassy/registry.py
calmjs/sassy/runtime.py
calmjs/sassy/toolchain.py
calmjs/sassy/testing/__init__.py
calmjs/sassy/testing/index.scss
calmjs/sassy/testing/utils.py
calmjs/sassy/tests/__init__.py
calmjs/sassy/tests/test_cli.py
calmjs/sassy/tests/test_dist.py
calmjs/sassy/tests/test_integration.py
calmjs/sassy/tests/test_libsass.py
calmjs/sassy/tests/test_registry.py
calmjs/sassy/tests/test_runtime.py
calmjs/sassy/tests/test_toolchain.py
calmjs.sassy-1.0.2.dist-info/METADATA
calmjs.sassy-1.0.2.dist-info/RECORD
calmjs.sassy-1.0.2.dist-info/WHEEL
calmjs.sassy-1.0.2.dist-info/calmjs_scss_module_registry.txt
calmjs.sassy-1.0.2.dist-info/entry_points.txt
calmjs.sassy-1.0.2.dist-info/namespace_packages.txt
calmjs.sassy-1.0.2.dist-info/top_level.txt
