Metadata-Version: 2.1
Name: calmjs.sassy
Version: 1.0.2
Summary: Package for extending the Calmjs framework to support the usage of sass in a manner that crosses Python package boundaries by exposing an import system that mimics the package namespaces available within a given Python environment.
Home-page: https://github.com/calmjs/calmjs.sassy
Author: Tommy Yu
Author-email: tommy.yu@auckland.ac.nz
License: GPL
Platform: UNKNOWN
Classifier: Development Status :: 5 - Production/Stable
Classifier: Environment :: Console
Classifier: Environment :: Plugins
Classifier: Framework :: Setuptools Plugin
Classifier: Intended Audience :: Developers
Classifier: License :: OSI Approved :: GNU General Public License v2 or later (GPLv2+)
Classifier: Operating System :: MacOS :: MacOS X
Classifier: Operating System :: Microsoft :: Windows
Classifier: Operating System :: POSIX
Classifier: Operating System :: POSIX :: BSD
Classifier: Operating System :: POSIX :: Linux
Classifier: Operating System :: OS Independent
Classifier: Programming Language :: Python
Classifier: Programming Language :: Python :: 2
Classifier: Programming Language :: Python :: 2.7
Classifier: Programming Language :: Python :: 3
Classifier: Programming Language :: Python :: 3.3
Classifier: Programming Language :: Python :: 3.4
Classifier: Programming Language :: Python :: 3.5
Classifier: Programming Language :: Python :: 3.6
Classifier: Programming Language :: Python :: Implementation :: CPython
Classifier: Programming Language :: Python :: Implementation :: PyPy
Classifier: Topic :: Software Development :: Build Tools
Classifier: Topic :: System :: Software Distribution
Classifier: Topic :: Utilities
Provides-Extra: libsass
Requires-Dist: calmjs (>=3.2.0)
Provides-Extra: libsass
Requires-Dist: libsass (>=0.11.0); extra == 'libsass'
